{"image15009.jpg116675":{"filename":"image15009.jpg","size":116675,"regions":[{"shape_attributes":{"name":"polygon","all_points_x":[413,397,388,380,372,378,390,389,386,374,371,367,365,370,377,383,385,376,365,362,359,357,358,366,375,380,384,386,395,399,396,391,386,378,373,370,372,358,360,364,372,376,378,378,376,381,389,395,394,395,401,427,436,441,444,445,444,444,442,441,426,417,410,405,404,408,413,416,421,427,437,441,441,424,412,401,401,419,427,433,438,441,442,437,430,421],"all_points_y":[28,31,33,40,54,55,61,66,67,61,60,64,77,71,70,74,81,82,77,79,93,107,124,120,114,111,114,112,120,126,127,130,130,130,128,123,115,125,132,143,148,150,162,169,176,171,168,166,161,156,150,135,130,124,115,107,103,94,90,87,86,87,86,83,83,81,79,79,81,86,87,86,81,67,66,71,62,59,63,68,79,81,66,48,36,31]},"region_attributes":{"name":"not_defined","type":"unknown","image_quality":{"good":true,"frontal":true,"good_illumination":true}}},{"shape_attributes":{"name":"polygon","all_points_x":[306,309,316,319,321,321,319,322,330,344,357,363,355,350,345,344,346,347,344,343,339,339,339,337,337,334,330,330,307,302,297,294,289,284,283,282,283,286,285,284,291,299,303],"all_points_y":[442,435,431,431,433,440,451,453,454,458,456,454,477,489,521,547,555,597,605,609,609,615,619,621,625,626,623,616,612,604,601,594,586,583,583,579,570,535,527,521,511,487,466]},"region_attributes":{"name":"not_defined","type":"unknown","image_quality":{"good":true,"frontal":true,"good_illumination":true}}},{"shape_attributes":{"name":"polygon","all_points_x":[287,293,309,327,327,314,307,296,282,275,281,284],"all_points_y":[966,972,979,982,993,999,1000,999,989,983,978,974]},"region_attributes":{"name":"not_defined","type":"unknown","image_quality":{"good":true,"frontal":true,"good_illumination":true}}},{"shape_attributes":{"name":"polygon","all_points_x":[247,263,273,283,286,287,286,269,261],"all_points_y":[1002,993,1002,1010,1015,1024,1026,1026,1015]},"region_attributes":{"name":"not_defined","type":"unknown","image_quality":{"good":true,"frontal":true,"good_illumination":true}}},{"shape_attributes":{"name":"polygon","all_points_x":[303,306,316,328,329,327,323,319,314],"all_points_y":[1030,1021,1015,1008,1015,1022,1028,1030,1031]},"region_attributes":{"name":"not_defined","type":"unknown","image_quality":{"good":true,"frontal":true,"good_illumination":true}}},{"shape_attributes":{"name":"polygon","all_points_x":[204,207,211,214,204,197,191,189,189,191,189,189,189,191],"all_points_y":[1031,1022,1014,1011,1010,1010,1011,1013,1018,1020,1023,1026,1028,1030]},"region_attributes":{"name":"not_defined","type":"unknown","image_quality":{"good":true,"frontal":true,"good_illumination":true}}},{"shape_attributes":{"name":"polygon","all_points_x":[339,341,339,340,345,349,357,362,367,372,360,353,345,339],"all_points_y":[1053,1058,1061,1064,1066,1066,1071,1071,1073,1048,1046,1046,1047,1050]},"region_attributes":{"name":"not_defined","type":"unknown","image_quality":{"good":true,"frontal":true,"good_illumination":true}}},{"shape_attributes":{"name":"polygon","all_points_x":[427,436,452,469,478,479,473,465,452,446,447,435,433,428,423,421],"all_points_y":[1009,1014,1018,1015,1011,1019,1025,1031,1033,1032,1031,1026,1026,1023,1020,1015]},"region_attributes":{"name":"not_defined","type":"unknown","image_quality":{"good":true,"frontal":true,"good_illumination":true}}},{"shape_attributes":{"name":"polygon","all_points_x":[466,467,472,483,482,482,478,474],"all_points_y":[1063,1053,1044,1036,1049,1055,1058,1063]},"region_attributes":{"name":"not_defined","type":"unknown","image_quality":{"good":true,"frontal":true,"good_illumination":true}}},{"shape_attributes":{"name":"polygon","all_points_x":[413,403,402,413,427,436,436,448,448,448,443,428,429],"all_points_y":[1026,1032,1037,1043,1056,1068,1071,1067,1059,1052,1049,1044,1041]},"region_attributes":{"name":"not_defined","type":"unknown","image_quality":{"good":true,"frontal":true,"good_illumination":true}}}],"file_attributes":{"caption":"","public_domain":"no","image_url":""}}}