{"image14095.jpg63509":{"filename":"image14095.jpg","size":63509,"regions":[{"shape_attributes":{"name":"polygon","all_points_x":[397,398,392],"all_points_y":[66,83,81]},"region_attributes":{"name":"not_defined","type":"unknown","image_quality":{"good":true,"frontal":true,"good_illumination":true}}},{"shape_attributes":{"name":"polygon","all_points_x":[397,394,404,404,399,396,397,385,392,393,388,387,382,368,359,348,343,341,329,308,323,327,339,339,344,355,371,365,375,378,383,388,390],"all_points_y":[94,103,121,127,129,130,136,141,148,150,153,164,169,167,163,163,169,169,157,155,138,119,125,147,151,132,122,159,159,125,112,102,91]},"region_attributes":{"name":"not_defined","type":"unknown","image_quality":{"good":true,"frontal":true,"good_illumination":true}}},{"shape_attributes":{"name":"polygon","all_points_x":[341,330,324,336,338],"all_points_y":[93,95,116,121,104]},"region_attributes":{"name":"not_defined","type":"unknown","image_quality":{"good":true,"frontal":true,"good_illumination":true}}},{"shape_attributes":{"name":"polygon","all_points_x":[420,430,446,457,446,440,431,431],"all_points_y":[504,494,481,525,532,537,537,524]},"region_attributes":{"name":"not_defined","type":"unknown","image_quality":{"good":true,"frontal":true,"good_illumination":true}}},{"shape_attributes":{"name":"polygon","all_points_x":[432,447,462,463,475,468,445,443,431,430,427,425,430,439,441,446,436,423,424,431,434,437,434],"all_points_y":[550,552,548,546,575,598,613,611,612,608,607,604,600,601,597,586,597,603,596,592,586,580,555]},"region_attributes":{"name":"not_defined","type":"unknown","image_quality":{"good":true,"frontal":true,"good_illumination":true}}},{"shape_attributes":{"name":"polygon","all_points_x":[200,196,199,194,202,203,203,202,204],"all_points_y":[497,527,540,570,587,570,532,508,498]},"region_attributes":{"name":"not_defined","type":"unknown","image_quality":{"good":true,"frontal":true,"good_illumination":true}}},{"shape_attributes":{"name":"polygon","all_points_x":[314,315,317,314,308,296,277,270,273,277,277,275,276,286,296,304],"all_points_y":[970,991,998,1011,1020,1015,1015,1014,1003,996,991,984,978,984,981,978]},"region_attributes":{"name":"not_defined","type":"unknown","image_quality":{"good":true,"frontal":true,"good_illumination":true}}},{"shape_attributes":{"name":"polygon","all_points_x":[411,410,411,408,391,370,365,366,372,378,388,402],"all_points_y":[973,996,1013,1024,1018,1018,1011,1002,991,979,979,979]},"region_attributes":{"name":"not_defined","type":"unknown","image_quality":{"good":true,"frontal":true,"good_illumination":true}}}],"file_attributes":{"caption":"","public_domain":"no","image_url":""}}}